omnimodkit/README.md
omnimodkit/__init__.py
omnimodkit/ai_config.py
omnimodkit/audio_generation_model/__init__.py
omnimodkit/audio_generation_model/audio_generation_model.py
omnimodkit/audio_recognition_model/__init__.py
omnimodkit/audio_recognition_model/audio_recognition_model.py
omnimodkit/base_toolkit_model.py
omnimodkit/data/default_ai_config.yaml
omnimodkit/image_generation_model/__init__.py
omnimodkit/image_generation_model/image_generation_model.py
omnimodkit/models_toolkit.py
omnimodkit/moderation.py
omnimodkit/omnimodel.py
omnimodkit/text_model/__init__.py
omnimodkit/text_model/text_model.py
omnimodkit/vision_model/__init__.py
omnimodkit/vision_model/vision_model.py
omnimodkit-0.0.9.dist-info/METADATA
omnimodkit-0.0.9.dist-info/WHEEL
omnimodkit-0.0.9.dist-info/licenses/LICENSE
omnimodkit-0.0.9.dist-info/RECORD
